{"title": "Makise Kurisu (rian_95)", "id": "tg-423386142189027335", "net.maunium.telegram.pack": {"short_name": "LabMember004", "hash": "561968807"}, "stickers": [{"body": "🙁", "url": "mxc://m.sleroq.link/MerIVbieIWbEuaBPTksiQtHl", "info": {"w": 215, "h": 256, "size": 202528, "mimetype": "image/png", "thumbnail_url": "mxc://m.sleroq.link/MerIVbieIWbEuaBPTksiQtHl", "thumbnail_info": {"w": 215, "h": 256, "size": 202528, "mimetype": "image/png"}}, "msgtype": "m.sticker", "id": "tg-423386142189029610", "net.maunium.telegram.sticker": {"pack": {"id": "423386142189027335", "short_name": "LabMember004"}, "id": "423386142189029610", "emoticons": ["🙁"]}}, {"body": "😅", "url": "mxc://m.sleroq.link/pmWYToRWcDQmxfNUpIiKhgWZ", "info": {"w": 256, "h": 240, "size": 228108, "mimetype": "image/png", "thumbnail_url": "mxc://m.sleroq.link/pmWYToRWcDQmxfNUpIiKhgWZ", "thumbnail_info": {"w": 256, "h": 240, "size": 228108, "mimetype": "image/png"}}, "msgtype": "m.sticker", "id": "tg-423386142189029612", "net.maunium.telegram.sticker": {"pack": {"id": "423386142189027335", "short_name": "LabMember004"}, "id": "423386142189029612", "emoticons": ["😅"]}}, {"body": "😣", "url": "mxc://m.sleroq.link/UOgfXNxHaExzuqAhsEBIVCWZ", "info": {"w": 249, "h": 256, "size": 160725, "mimetype": "image/png", "thumbnail_url": "mxc://m.sleroq.link/UOgfXNxHaExzuqAhsEBIVCWZ", "thumbnail_info": {"w": 249, "h": 256, "size": 160725, "mimetype": "image/png"}}, "msgtype": "m.sticker", "id": "tg-423386142189029614", "net.maunium.telegram.sticker": {"pack": {"id": "423386142189027335", "short_name": "LabMember004"}, "id": "423386142189029614", "emoticons": ["😣"]}}, {"body": "🙁", "url": "mxc://m.sleroq.link/MFLdjWDUJkbBnNIoxlNylCTE", "info": {"w": 204, "h": 256, "size": 130800, "mimetype": "image/png", "thumbnail_url": "mxc://m.sleroq.link/MFLdjWDUJkbBnNIoxlNylCTE", "thumbnail_info": {"w": 204, "h": 256, "size": 130800, "mimetype": "image/png"}}, "msgtype": "m.sticker", "id": "tg-423386142189029616", "net.maunium.telegram.sticker": {"pack": {"id": "423386142189027335", "short_name": "LabMember004"}, "id": "423386142189029616", "emoticons": ["🙁"]}}, {"body": "😨", "url": "mxc://m.sleroq.link/VeQixIlyMyyZnpqSQVCFhRYz", "info": {"w": 256, "h": 145, "size": 101011, "mimetype": "image/png", "thumbnail_url": "mxc://m.sleroq.link/VeQixIlyMyyZnpqSQVCFhRYz", "thumbnail_info": {"w": 256, "h": 145, "size": 101011, "mimetype": "image/png"}}, "msgtype": "m.sticker", "id": "tg-423386142189029618", "net.maunium.telegram.sticker": {"pack": {"id": "423386142189027335", "short_name": "LabMember004"}, "id": "423386142189029618", "emoticons": ["😨"]}}, {"body": "😦", "url": "mxc://m.sleroq.link/dWDmgWWXIXHwtXdGiCAkBmNi", "info": {"w": 256, "h": 200, "size": 150771, "mimetype": "image/png", "thumbnail_url": "mxc://m.sleroq.link/dWDmgWWXIXHwtXdGiCAkBmNi", "thumbnail_info": {"w": 256, "h": 200, "size": 150771, "mimetype": "image/png"}}, "msgtype": "m.sticker", "id": "tg-423386142189029620", "net.maunium.telegram.sticker": {"pack": {"id": "423386142189027335", "short_name": "LabMember004"}, "id": "423386142189029620", "emoticons": ["😦"]}}, {"body": "😰", "url": "mxc://m.sleroq.link/vGhYNVgyCRrvCkNVqxXSRTSY", "info": {"w": 256, "h": 154, "size": 103062, "mimetype": "image/png", "thumbnail_url": "mxc://m.sleroq.link/vGhYNVgyCRrvCkNVqxXSRTSY", "thumbnail_info": {"w": 256, "h": 154, "size": 103062, "mimetype": "image/png"}}, "msgtype": "m.sticker", "id": "tg-423386142189029622", "net.maunium.telegram.sticker": {"pack": {"id": "423386142189027335", "short_name": "LabMember004"}, "id": "423386142189029622", "emoticons": ["😰"]}}, {"body": "☺️", "url": "mxc://m.sleroq.link/YkFNSwsSbvlxuHJAEAGRNCIq", "info": {"w": 256, "h": 240, "size": 131070, "mimetype": "image/png", "thumbnail_url": "mxc://m.sleroq.link/YkFNSwsSbvlxuHJAEAGRNCIq", "thumbnail_info": {"w": 256, "h": 240, "size": 131070, "mimetype": "image/png"}}, "msgtype": "m.sticker", "id": "tg-423386142189029624", "net.maunium.telegram.sticker": {"pack": {"id": "423386142189027335", "short_name": "LabMember004"}, "id": "423386142189029624", "emoticons": ["☺"]}}, {"body": "💬", "url": "mxc://m.sleroq.link/BMsytUkSUWyzGuqGYcizpXFw", "info": {"w": 249, "h": 256, "size": 140970, "mimetype": "image/png", "thumbnail_url": "mxc://m.sleroq.link/BMsytUkSUWyzGuqGYcizpXFw", "thumbnail_info": {"w": 249, "h": 256, "size": 140970, "mimetype": "image/png"}}, "msgtype": "m.sticker", "id": "tg-423386142189029626", "net.maunium.telegram.sticker": {"pack": {"id": "423386142189027335", "short_name": "LabMember004"}, "id": "423386142189029626", "emoticons": ["💬"]}}, {"body": "😒", "url": "mxc://m.sleroq.link/YlNjHbwiPFEvKnfiGroYODjI", "info": {"w": 256, "h": 152, "size": 105961, "mimetype": "image/png", "thumbnail_url": "mxc://m.sleroq.link/YlNjHbwiPFEvKnfiGroYODjI", "thumbnail_info": {"w": 256, "h": 152, "size": 105961, "mimetype": "image/png"}}, "msgtype": "m.sticker", "id": "tg-423386142189029511", "net.maunium.telegram.sticker": {"pack": {"id": "423386142189027335", "short_name": "LabMember004"}, "id": "423386142189029511", "emoticons": ["😒"]}}, {"body": "❓", "url": "mxc://m.sleroq.link/RTTewrJtgdiajJPeOOVUWszM", "info": {"w": 242, "h": 256, "size": 151418, "mimetype": "image/png", "thumbnail_url": "mxc://m.sleroq.link/RTTewrJtgdiajJPeOOVUWszM", "thumbnail_info": {"w": 242, "h": 256, "size": 151418, "mimetype": "image/png"}}, "msgtype": "m.sticker", "id": "tg-423386142189029629", "net.maunium.telegram.sticker": {"pack": {"id": "423386142189027335", "short_name": "LabMember004"}, "id": "423386142189029629", "emoticons": ["❓"]}}, {"body": "❗", "url": "mxc://m.sleroq.link/POqgaqIJoORuzSWJRmYdgJOw", "info": {"w": 242, "h": 256, "size": 156312, "mimetype": "image/png", "thumbnail_url": "mxc://m.sleroq.link/POqgaqIJoORuzSWJRmYdgJOw", "thumbnail_info": {"w": 242, "h": 256, "size": 156312, "mimetype": "image/png"}}, "msgtype": "m.sticker", "id": "tg-423386142189029631", "net.maunium.telegram.sticker": {"pack": {"id": "423386142189027335", "short_name": "LabMember004"}, "id": "423386142189029631", "emoticons": ["❗"]}}, {"body": "😠", "url": "mxc://m.sleroq.link/hYKEtACtnbWsZevAbvvQxbFv", "info": {"w": 242, "h": 256, "size": 131595, "mimetype": "image/png", "thumbnail_url": "mxc://m.sleroq.link/hYKEtACtnbWsZevAbvvQxbFv", "thumbnail_info": {"w": 242, "h": 256, "size": 131595, "mimetype": "image/png"}}, "msgtype": "m.sticker", "id": "tg-423386142189029633", "net.maunium.telegram.sticker": {"pack": {"id": "423386142189027335", "short_name": "LabMember004"}, "id": "423386142189029633", "emoticons": ["😠"]}}, {"body": "😒", "url": "mxc://m.sleroq.link/YcWXlJTTguzbhmrWscOOSoAH", "info": {"w": 242, "h": 256, "size": 118160, "mimetype": "image/png", "thumbnail_url": "mxc://m.sleroq.link/YcWXlJTTguzbhmrWscOOSoAH", "thumbnail_info": {"w": 242, "h": 256, "size": 118160, "mimetype": "image/png"}}, "msgtype": "m.sticker", "id": "tg-423386142189029635", "net.maunium.telegram.sticker": {"pack": {"id": "423386142189027335", "short_name": "LabMember004"}, "id": "423386142189029635", "emoticons": ["😒"]}}, {"body": "👍", "url": "mxc://m.sleroq.link/wFWSvqUSrjKFcZDmIPgNCByv", "info": {"w": 256, "h": 166, "size": 130123, "mimetype": "image/png", "thumbnail_url": "mxc://m.sleroq.link/wFWSvqUSrjKFcZDmIPgNCByv", "thumbnail_info": {"w": 256, "h": 166, "size": 130123, "mimetype": "image/png"}}, "msgtype": "m.sticker", "id": "tg-423386142189029637", "net.maunium.telegram.sticker": {"pack": {"id": "423386142189027335", "short_name": "LabMember004"}, "id": "423386142189029637", "emoticons": ["👍"]}}, {"body": "😞", "url": "mxc://m.sleroq.link/oxFOmHokebBKjWSbQzftSYKF", "info": {"w": 256, "h": 146, "size": 144476, "mimetype": "image/png", "thumbnail_url": "mxc://m.sleroq.link/oxFOmHokebBKjWSbQzftSYKF", "thumbnail_info": {"w": 256, "h": 146, "size": 144476, "mimetype": "image/png"}}, "msgtype": "m.sticker", "id": "tg-423386142189029639", "net.maunium.telegram.sticker": {"pack": {"id": "423386142189027335", "short_name": "LabMember004"}, "id": "423386142189029639", "emoticons": ["😞"]}}, {"body": "💃", "url": "mxc://m.sleroq.link/IyboBipsyZTXFmIipvcPWeJQ", "info": {"w": 256, "h": 247, "size": 163671, "mimetype": "image/png", "thumbnail_url": "mxc://m.sleroq.link/IyboBipsyZTXFmIipvcPWeJQ", "thumbnail_info": {"w": 256, "h": 247, "size": 163671, "mimetype": "image/png"}}, "msgtype": "m.sticker", "id": "tg-423386142189029641", "net.maunium.telegram.sticker": {"pack": {"id": "423386142189027335", "short_name": "LabMember004"}, "id": "423386142189029641", "emoticons": ["💃"]}}, {"body": "😫", "url": "mxc://m.sleroq.link/CmFnvgnvZxRkqHQaVdvnsmSD", "info": {"w": 256, "h": 153, "size": 111604, "mimetype": "image/png", "thumbnail_url": "mxc://m.sleroq.link/CmFnvgnvZxRkqHQaVdvnsmSD", "thumbnail_info": {"w": 256, "h": 153, "size": 111604, "mimetype": "image/png"}}, "msgtype": "m.sticker", "id": "tg-423386142189029643", "net.maunium.telegram.sticker": {"pack": {"id": "423386142189027335", "short_name": "LabMember004"}, "id": "423386142189029643", "emoticons": ["😫"]}}, {"body": "😨", "url": "mxc://m.sleroq.link/PwlTYYtXYMdmKhBkaIlMMmby", "info": {"w": 256, "h": 208, "size": 131596, "mimetype": "image/png", "thumbnail_url": "mxc://m.sleroq.link/PwlTYYtXYMdmKhBkaIlMMmby", "thumbnail_info": {"w": 256, "h": 208, "size": 131596, "mimetype": "image/png"}}, "msgtype": "m.sticker", "id": "tg-423386142189029645", "net.maunium.telegram.sticker": {"pack": {"id": "423386142189027335", "short_name": "LabMember004"}, "id": "423386142189029645", "emoticons": ["😨"]}}, {"body": "😳", "url": "mxc://m.sleroq.link/wBNcwHjEpgWwoLENQYnPjcMF", "info": {"w": 256, "h": 217, "size": 121477, "mimetype": "image/png", "thumbnail_url": "mxc://m.sleroq.link/wBNcwHjEpgWwoLENQYnPjcMF", "thumbnail_info": {"w": 256, "h": 217, "size": 121477, "mimetype": "image/png"}}, "msgtype": "m.sticker", "id": "tg-423386142189029647", "net.maunium.telegram.sticker": {"pack": {"id": "423386142189027335", "short_name": "LabMember004"}, "id": "423386142189029647", "emoticons": ["😳"]}}, {"body": "😒", "url": "mxc://m.sleroq.link/OTHZGqMstsEFyLCAIoYbshRf", "info": {"w": 256, "h": 241, "size": 222325, "mimetype": "image/png", "thumbnail_url": "mxc://m.sleroq.link/OTHZGqMstsEFyLCAIoYbshRf", "thumbnail_info": {"w": 256, "h": 241, "size": 222325, "mimetype": "image/png"}}, "msgtype": "m.sticker", "id": "tg-423386142189029649", "net.maunium.telegram.sticker": {"pack": {"id": "423386142189027335", "short_name": "LabMember004"}, "id": "423386142189029649", "emoticons": ["😒"]}}, {"body": "🤔", "url": "mxc://m.sleroq.link/qAodwHamIKiOJFYhMgmysAdo", "info": {"w": 216, "h": 256, "size": 161990, "mimetype": "image/png", "thumbnail_url": "mxc://m.sleroq.link/qAodwHamIKiOJFYhMgmysAdo", "thumbnail_info": {"w": 216, "h": 256, "size": 161990, "mimetype": "image/png"}}, "msgtype": "m.sticker", "id": "tg-423386142189029651", "net.maunium.telegram.sticker": {"pack": {"id": "423386142189027335", "short_name": "LabMember004"}, "id": "423386142189029651", "emoticons": ["🤔"]}}, {"body": "😤", "url": "mxc://m.sleroq.link/XHqIXHmceIWVzfYEBRCqeDWm", "info": {"w": 256, "h": 229, "size": 148714, "mimetype": "image/png", "thumbnail_url": "mxc://m.sleroq.link/XHqIXHmceIWVzfYEBRCqeDWm", "thumbnail_info": {"w": 256, "h": 229, "size": 148714, "mimetype": "image/png"}}, "msgtype": "m.sticker", "id": "tg-423386142189029654", "net.maunium.telegram.sticker": {"pack": {"id": "423386142189027335", "short_name": "LabMember004"}, "id": "423386142189029654", "emoticons": ["😤"]}}, {"body": "😩", "url": "mxc://m.sleroq.link/KSZkcOAmDeepVzcTwJRCWPMz", "info": {"w": 256, "h": 232, "size": 154192, "mimetype": "image/png", "thumbnail_url": "mxc://m.sleroq.link/KSZkcOAmDeepVzcTwJRCWPMz", "thumbnail_info": {"w": 256, "h": 232, "size": 154192, "mimetype": "image/png"}}, "msgtype": "m.sticker", "id": "tg-423386142189029656", "net.maunium.telegram.sticker": {"pack": {"id": "423386142189027335", "short_name": "LabMember004"}, "id": "423386142189029656", "emoticons": ["😩"]}}, {"body": "🙂", "url": "mxc://m.sleroq.link/TPSwHLuTJmvCHyLTNKfhqZUR", "info": {"w": 256, "h": 201, "size": 115074, "mimetype": "image/png", "thumbnail_url": "mxc://m.sleroq.link/TPSwHLuTJmvCHyLTNKfhqZUR", "thumbnail_info": {"w": 256, "h": 201, "size": 115074, "mimetype": "image/png"}}, "msgtype": "m.sticker", "id": "tg-423386142189029658", "net.maunium.telegram.sticker": {"pack": {"id": "423386142189027335", "short_name": "LabMember004"}, "id": "423386142189029658", "emoticons": ["🙂"]}}, {"body": "😥", "url": "mxc://m.sleroq.link/hGQhLTgmOuQJQxHgGWFOHwTZ", "info": {"w": 256, "h": 178, "size": 110496, "mimetype": "image/png", "thumbnail_url": "mxc://m.sleroq.link/hGQhLTgmOuQJQxHgGWFOHwTZ", "thumbnail_info": {"w": 256, "h": 178, "size": 110496, "mimetype": "image/png"}}, "msgtype": "m.sticker", "id": "tg-423386142189029660", "net.maunium.telegram.sticker": {"pack": {"id": "423386142189027335", "short_name": "LabMember004"}, "id": "423386142189029660", "emoticons": ["😥"]}}, {"body": "👍", "url": "mxc://m.sleroq.link/GYLzcTrTPkEIHsSjahwPqMTB", "info": {"w": 256, "h": 203, "size": 153247, "mimetype": "image/png", "thumbnail_url": "mxc://m.sleroq.link/GYLzcTrTPkEIHsSjahwPqMTB", "thumbnail_info": {"w": 256, "h": 203, "size": 153247, "mimetype": "image/png"}}, "msgtype": "m.sticker", "id": "tg-423386142189029662", "net.maunium.telegram.sticker": {"pack": {"id": "423386142189027335", "short_name": "LabMember004"}, "id": "423386142189029662", "emoticons": ["👍"]}}, {"body": "❓", "url": "mxc://m.sleroq.link/LXJKHkntzoVMeOkosTWrbkkb", "info": {"w": 256, "h": 224, "size": 130963, "mimetype": "image/png", "thumbnail_url": "mxc://m.sleroq.link/LXJKHkntzoVMeOkosTWrbkkb", "thumbnail_info": {"w": 256, "h": 224, "size": 130963, "mimetype": "image/png"}}, "msgtype": "m.sticker", "id": "tg-423386142189029681", "net.maunium.telegram.sticker": {"pack": {"id": "423386142189027335", "short_name": "LabMember004"}, "id": "423386142189029681", "emoticons": ["😒", "❓", "😑"]}}, {"body": "😎", "url": "mxc://m.sleroq.link/XSkWAFUfFcwZMNYRiTipqwQc", "info": {"w": 256, "h": 218, "size": 139441, "mimetype": "image/png", "thumbnail_url": "mxc://m.sleroq.link/XSkWAFUfFcwZMNYRiTipqwQc", "thumbnail_info": {"w": 256, "h": 218, "size": 139441, "mimetype": "image/png"}}, "msgtype": "m.sticker", "id": "tg-423386142189029679", "net.maunium.telegram.sticker": {"pack": {"id": "423386142189027335", "short_name": "LabMember004"}, "id": "423386142189029679", "emoticons": ["😎"]}}, {"body": "😠", "url": "mxc://m.sleroq.link/jdpmJJSaOgZFoQIBKaoojVuz", "info": {"w": 256, "h": 226, "size": 122921, "mimetype": "image/png", "thumbnail_url": "mxc://m.sleroq.link/jdpmJJSaOgZFoQIBKaoojVuz", "thumbnail_info": {"w": 256, "h": 226, "size": 122921, "mimetype": "image/png"}}, "msgtype": "m.sticker", "id": "tg-423386142189029562", "net.maunium.telegram.sticker": {"pack": {"id": "423386142189027335", "short_name": "LabMember004"}, "id": "423386142189029562", "emoticons": ["😠"]}}, {"body": "😟", "url": "mxc://m.sleroq.link/jiEqxRlDlbVtGyKyIuoCXVhD", "info": {"w": 256, "h": 215, "size": 113277, "mimetype": "image/png", "thumbnail_url": "mxc://m.sleroq.link/jiEqxRlDlbVtGyKyIuoCXVhD", "thumbnail_info": {"w": 256, "h": 215, "size": 113277, "mimetype": "image/png"}}, "msgtype": "m.sticker", "id": "tg-423386142189029667", "net.maunium.telegram.sticker": {"pack": {"id": "423386142189027335", "short_name": "LabMember004"}, "id": "423386142189029667", "emoticons": ["😟"]}}, {"body": "😖", "url": "mxc://m.sleroq.link/vsSDNqAAlrAZjIbiSMKuawQO", "info": {"w": 256, "h": 187, "size": 108629, "mimetype": "image/png", "thumbnail_url": "mxc://m.sleroq.link/vsSDNqAAlrAZjIbiSMKuawQO", "thumbnail_info": {"w": 256, "h": 187, "size": 108629, "mimetype": "image/png"}}, "msgtype": "m.sticker", "id": "tg-423386142189029669", "net.maunium.telegram.sticker": {"pack": {"id": "423386142189027335", "short_name": "LabMember004"}, "id": "423386142189029669", "emoticons": ["😖"]}}, {"body": "😱", "url": "mxc://m.sleroq.link/dFaUpbIdtIGgwvjagtRdaVmB", "info": {"w": 256, "h": 160, "size": 143733, "mimetype": "image/png", "thumbnail_url": "mxc://m.sleroq.link/dFaUpbIdtIGgwvjagtRdaVmB", "thumbnail_info": {"w": 256, "h": 160, "size": 143733, "mimetype": "image/png"}}, "msgtype": "m.sticker", "id": "tg-423386142189029671", "net.maunium.telegram.sticker": {"pack": {"id": "423386142189027335", "short_name": "LabMember004"}, "id": "423386142189029671", "emoticons": ["😱"]}}, {"body": "😢", "url": "mxc://m.sleroq.link/uiascSqJylUpZglsOrbuLXfZ", "info": {"w": 256, "h": 160, "size": 119599, "mimetype": "image/png", "thumbnail_url": "mxc://m.sleroq.link/uiascSqJylUpZglsOrbuLXfZ", "thumbnail_info": {"w": 256, "h": 160, "size": 119599, "mimetype": "image/png"}}, "msgtype": "m.sticker", "id": "tg-423386142189029674", "net.maunium.telegram.sticker": {"pack": {"id": "423386142189027335", "short_name": "LabMember004"}, "id": "423386142189029674", "emoticons": ["😢"]}}, {"body": "😭", "url": "mxc://m.sleroq.link/okpMafeOWQUyGjYOdAExhZHV", "info": {"w": 256, "h": 211, "size": 127025, "mimetype": "image/png", "thumbnail_url": "mxc://m.sleroq.link/okpMafeOWQUyGjYOdAExhZHV", "thumbnail_info": {"w": 256, "h": 211, "size": 127025, "mimetype": "image/png"}}, "msgtype": "m.sticker", "id": "tg-423386142189029676", "net.maunium.telegram.sticker": {"pack": {"id": "423386142189027335", "short_name": "LabMember004"}, "id": "423386142189029676", "emoticons": ["😭"]}}]}